{
  "formatVersion": 1,
  "database": {
    "version": 3,
    "identityHash": "766c790e1d2d615815f8f00b25de92d8",
    "entities": [
      {
        "tableName": "GYMLOG_TABLE",
        "createSql": "CREATE TABLE IF NOT EXISTS `${TABLE_NAME}` (`mLogId` INTEGER PRIMARY KEY AUTOINCREMENT NOT NULL, `mExercise` TEXT, `mReps` INTEGER NOT NULL, `mWeight` REAL NOT NULL, `mDate` INTEGER, `mUserId` INTEGER NOT NULL)",
        "fields": [
          {
            "fieldPath": "mLogId",
            "columnName": "mLogId",
            "affinity": "INTEGER",
            "notNull": true
          },
          {
            "fieldPath": "mExercise",
            "columnName": "mExercise",
            "affinity": "TEXT",
            "notNull": false
          },
          {
            "fieldPath": "mReps",
            "columnName": "mReps",
            "affinity": "INTEGER",
            "notNull": true
          },
          {
            "fieldPath": "mWeight",
            "columnName": "mWeight",
            "affinity": "REAL",
            "notNull": true
          },
          {
            "fieldPath": "mDate",
            "columnName": "mDate",
            "affinity": "INTEGER",
            "notNull": false
          },
          {
            "fieldPath": "mUserId",
            "columnName": "mUserId",
            "affinity": "INTEGER",
            "notNull": true
          }
        ],
        "primaryKey": {
          "autoGenerate": true,
          "columnNames": [
            "mLogId"
          ]
        },
        "indices": [],
        "foreignKeys": []
      },
      {
        "tableName": "USER_TABLE",
        "createSql": "CREATE TABLE IF NOT EXISTS `${TABLE_NAME}` (`mUserId` INTEGER PRIMARY KEY AUTOINCREMENT NOT NULL, `mUserName` TEXT, `mPassword` TEXT)",
        "fields": [
          {
            "fieldPath": "mUserId",
            "columnName": "mUserId",
            "affinity": "INTEGER",
            "notNull": true
          },
          {
            "fieldPath": "mUserName",
            "columnName": "mUserName",
            "affinity": "TEXT",
            "notNull": false
          },
          {
            "fieldPath": "mPassword",
            "columnName": "mPassword",
            "affinity": "TEXT",
            "notNull": false
          }
        ],
        "primaryKey": {
          "autoGenerate": true,
          "columnNames": [
            "mUserId"
          ]
        },
        "indices": [],
        "foreignKeys": []
      },
      {
        "tableName": "PRODUCT_TABLE",
        "createSql": "CREATE TABLE IF NOT EXISTS `${TABLE_NAME}` (`mProductId` INTEGER PRIMARY KEY AUTOINCREMENT NOT NULL, `mProductName` TEXT, `mDescription` TEXT, `mPrice` REAL NOT NULL)",
        "fields": [
          {
            "fieldPath": "mProductId",
            "columnName": "mProductId",
            "affinity": "INTEGER",
            "notNull": true
          },
          {
            "fieldPath": "mProductName",
            "columnName": "mProductName",
            "affinity": "TEXT",
            "notNull": false
          },
          {
            "fieldPath": "mDescription",
            "columnName": "mDescription",
            "affinity": "TEXT",
            "notNull": false
          },
          {
            "fieldPath": "mPrice",
            "columnName": "mPrice",
            "affinity": "REAL",
            "notNull": true
          }
        ],
        "primaryKey": {
          "autoGenerate": true,
          "columnNames": [
            "mProductId"
          ]
        },
        "indices": [],
        "foreignKeys": []
      }
    ],
    "views": [],
    "setupQueries": [
      "CREATE TABLE IF NOT EXISTS room_master_table (id INTEGER PRIMARY KEY,identity_hash TEXT)",
      "INSERT OR REPLACE INTO room_master_table (id,identity_hash) VALUES(42, '766c790e1d2d615815f8f00b25de92d8')"
    ]
  }
}